CurrencyDataCrawler/__init__.py
CurrencyDataCrawler/client.py
CurrencyDataCrawler/crawl_currency.py
CurrencyDataCrawler/map_data.txt
CurrencyDataCrawler/update_local_id_map.py
A_Simple_Currency_Data_Crawler-1.0.1.dist-info/METADATA
A_Simple_Currency_Data_Crawler-1.0.1.dist-info/WHEEL
A_Simple_Currency_Data_Crawler-1.0.1.dist-info/top_level.txt
A_Simple_Currency_Data_Crawler-1.0.1.dist-info/RECORD
