Metadata-Version: 2.1
Name: A-Simple-Currency-Data-Crawler
Version: 1.0.1
Summary: A simple crawler for cryptocurrency data from CoinMarketCap.com
Home-page: https://github.com/deelsilcon/currency_crawler
Author: deelsilcon
Author-email: sudacsxyh@163.com
License: UNKNOWN
Platform: UNKNOWN
Classifier: Programming Language :: Python :: 3
Classifier: License :: OSI Approved :: MIT License
Classifier: Operating System :: OS Independent
Requires-Python: >=3.7
